nobuild-0.1.2.dist-info/METADATA
nobuild-0.1.2.dist-info/WHEEL
nobuild-0.1.2.dist-info/entry_points.txt
nobuild/__init__.py
nobuild/config.py
nobuild/distro/debian/README.md
nobuild/distro/debian/__init__.py
nobuild/distro/debian/generate.py
nobuild/distro/debian/init.py
nobuild/distro/debian/repo.py
nobuild/pkg.py
nobuild/types.py
nobuild-0.1.2.dist-info/RECORD
