Metadata-Version: 2.1
Name: nobuild
Version: 0.1.2
Summary: Distribution-independent custom image creation framework, inspired by FascodeNetwork 'LUBS-U'
Author-Email: AmaseCocoa <amase.cocoa@gmail.com>
License: MIT
Requires-Python: <3.14,>=3.13
Requires-Dist: typer-slim>=0.16.0
Requires-Dist: rich>=14.0.0
Requires-Dist: requests>=2.32.3
